MANIFEST.in
TODO.txt
bootstrap.py
buildout.cfg
setup.cfg
setup.py
src/svnpoller/README.txt
src/svnpoller/__init__.py
src/svnpoller/compat.py
src/svnpoller/decoder.py
src/svnpoller/sendmail.py
src/svnpoller/svnlog.py
src/svnpoller/svnpoller.ini
src/svnpoller/svnpoller.py
src/svnpoller.egg-info/PKG-INFO
src/svnpoller.egg-info/SOURCES.txt
src/svnpoller.egg-info/dependency_links.txt
src/svnpoller.egg-info/entry_points.txt
src/svnpoller.egg-info/requires.txt
src/svnpoller.egg-info/top_level.txt
src/svnpoller/tests/__init__.py
src/svnpoller/tests/base.py
src/svnpoller/tests/test_sendmail.py
src/svnpoller/tests/test_svnlog.py
src/svnpoller/tests/test_svnpoller.py
src/svnpoller/tests/fixtures/diff-516.xml
src/svnpoller/tests/fixtures/diff-632.xml
src/svnpoller/tests/fixtures/diff-654-655.xml
src/svnpoller/tests/fixtures/diff-663-664.xml
src/svnpoller/tests/fixtures/diff-666-667.xml
src/svnpoller/tests/fixtures/diff-667-668.xml
src/svnpoller/tests/fixtures/diff-669-670.xml
src/svnpoller/tests/fixtures/info-1.xml
src/svnpoller/tests/fixtures/log-1-HEAD.xml
src/svnpoller/tests/fixtures/log-516.xml
src/svnpoller/tests/fixtures/log-632.xml
src/svnpoller/tests/fixtures/log-655.xml
src/svnpoller/tests/fixtures/log-664.xml
src/svnpoller/tests/fixtures/log-667.xml
src/svnpoller/tests/fixtures/log-668.xml
src/svnpoller/tests/fixtures/log-670.xml