Metadata-Version: 1.0
Name: svnpoller
Version: 0.0.10
Summary: polling svn repository and notify by email.
Home-page: http://bitbucket.org/shimizukawa/svnpoller
Author: Takayuki SHIMIZUKAWA
Author-email: shimizukawa at gmail.com
License: PSL
Keywords: subversion,svn,poll,notify
Platform: UNKNOWN
Classifier: Development Status :: 4 - Beta
Classifier: Intended Audience :: System Administrators
Classifier: License :: OSI Approved :: Python Software Foundation License
Classifier: Programming Language :: Python
Classifier: Topic :: Software Development
